LICENSE
MANIFEST.in
README.md
debug.py
setup.py
PharmacoDI/__init__.py
PharmacoDI/build_all_pset_tables.py
PharmacoDI/build_cellosaurus.py
PharmacoDI/build_clinical_trial_tables.py
PharmacoDI/build_dataset_join_tables.py
PharmacoDI/build_experiment_tables.py
PharmacoDI/build_gene_compound_tissue_dataset_tables.py
PharmacoDI/build_meta_tables.py
PharmacoDI/build_primary_pset_tables.py
PharmacoDI/build_synonym_tables.py
PharmacoDI/build_target_tables.py
PharmacoDI/combine_pset_tables.py
PharmacoDI/download_canonical_psets.py
PharmacoDI/download_gene_signatures.py
PharmacoDI/download_psets.py
PharmacoDI/get_chembl_compound_targets.py
PharmacoDI/get_chembl_targets.py
PharmacoDI/get_gene_targets.py
PharmacoDI/get_target_annotations.py
PharmacoDI/map_genes_to_genomic_coordinates.py
PharmacoDI/read_pset.py
PharmacoDI/write_pset_table.py
PharmacoDI.egg-info/PKG-INFO
PharmacoDI.egg-info/SOURCES.txt
PharmacoDI.egg-info/dependency_links.txt
PharmacoDI.egg-info/not-zip-safe
PharmacoDI.egg-info/requires.txt
PharmacoDI.egg-info/top_level.txt
PharmacoDI/.deprecated/pset_to_db_tables.py
PharmacoDI/.deprecated/pset_to_py.py