Metadata-Version: 1.0
Name: PharmacoDI
Version: 0.0.5
Summary: Tools for processing R PharmacoSet objects into .csv files of PharmacoDB database tables.
Home-page: https://github.com/bhklab/DataIngestion/tree/master/PharmacoDI
Author: Evgeniya Gorobets, Christopher Eeles, Benjamin Haibe-Kains
Author-email: christopher.eeles@uhnresearch.ca, benjamin.haibe.kains@utoronto.ca
License: MIT
Platform: UNKNOWN
